{
  "mudurluk": "Ankara",
  "ilan_sira_no": "14736",
  "mersis_no": "0786053466300001",
  "sicil_no": "485373",
  "ticaret_unvani": "SUMER ENTEGRE ET SANAYI VE TICARET ANONIM ŞIRKETİ",
  "adres": "Güzelhisar Mah. Yıldırım Beyazıt Cad. No: 65A Akyurt/Ankara",
  "metin": "Yukarıda bilgileri verilen şirket ile ılgılı olarak aşağıda belirtilen hususlar müdürlüğümüze\nibraz edilen belgelere istinaden ve Türk Ticaret Kanunu'na uygun olarak 27.2.2025\ntarihinde resen tescil edildiği ilan olunur.\nTescil Edilen Hususlar: Kayyım (Yönetim Kurulu/Yetkililer)\nTescile Delil Olan Belgeler:\n26.2.2025 tarihli E-81514179-100-120219 sayılı Tasarruf Mevduatı Sigorta Fonu İştirakler\nve Gayrimenkuller Daire Başkanlığı Mahkeme Kararı\n26.2.2025 tarihli E-81514179-100-120219 sayılı Tasarruf Mevduatı Sigorta Fonu İştirakler\nve Gayrimenkuller Daire Başkanlığı Mahkeme Kararı\n26.2.2025 tarihli E-81514179-100-120219 sayılı Tasarruf Mevduatı Sigorta Fonu İştirakler\nve Gayrimenkuller Daire Başkanlığı Mahkeme Kararı\n26.2.2025 tarihli E-81514179-100-120219 sayılı Tasarruf Mevduatı Sigorta Fonu İştirakler\nve Gayrimenkuller Daire Başkanlığı Mahkeme Kararı\n26.2.2025 tarihli E-81514179-100-120219 sayılı Tasarruf Mevduatı Sigorta Fonu İştirakler\nve Gayrimenkuller Daire Başkanlığı Mahkeme Kararı\n26.2.2025 tarihli E-81514179-100-120219 sayılı Tasarruf Mevduatı Sigorta Fonu İştirakler\nve Gayrimenkuller Daire Başkanlığı Mahkeme Kararı\n26.2.2025 tarihli E-81514179-100-120219 sayılı Tasarruf Mevduatı Sigorta Fonu İştirakler\nve Gayrimenkuller Daire Başkanlığı Mahkeme Kararı\n26.2.2025 tarihli E-81514179-100-120219 sayılı Tasarruf Mevduatı Sigorta Fonu İştirakler\nve Gayrimenkuller Daire Başkanlığı Mahkeme Kararı\n26.2.2025 tarihli E-81514179-100-120219 sayılı Tasarruf Mevduatı Sigorta Fonu İştirakler\nve Gayrimenkuller Daire Başkanlığı Mahkeme Kararı\n26.2.2025 tarıhlı E-81514179-100-120219 sayılı Tasarruf Mevduatı Sigorta Fonu iştirakler\nve Gayrimenkuller Daire Başkanlığı Mahkeme Kararı\n26.2.2025 tarihli E-81514179-100-120219 sayılı Tasarruf Mevduatı Sigorta Fonu İştirakler\nve Gayrimenkuller Daire Başkanlığı Mahkeme Kararı\n26.2.2025 tarihli E-81514179-100-120219 sayılı Tasarruf Mevduatı Sigorta Fonu İştirakler\nve Gayrimenkuller Daire Başkanlığı Mahkeme Kararı\n26.2.2025 tarihli E-81514179-100-120219 sayılı Tasarruf Mevduatı Sigorta Fonu İştirakler\nve Gayrimenkuller Daire Başkanlığı Mahkeme Kararı\n26.2.2025 tarihli E-81514179-100-120219 sayılı Tasarruf Mevduatı Sigorta Fonu İştirakler\nve Gayrimenkuller Daire Başkanlığı Mahkeme Kararı\n26.2.2025 tarihli E-81514179-100-120219 sayılı Tasarruf Mevduatı Sigorta Fonu İştirakler\nve Gayrimenkuller Daire Başkanlığı Mahkeme Kararı\n26.2.2025 tarıhlı k-5151417/9-100-120219 sayılı lasarrut Mevduatı Sigorta Fonu Iştırakler\nve Gayrimenkuller Daire Başkanlığı Mahkeme Kararı\n26.2.2025 tarıhlı E-81514179-100-120219 sayılı Tasarruf Mevduatı Sigorta Fonu iştirakler\nve Gayrimenkuller Daire Başkanlığı Mahkeme Kararı\n26.2.2025 tarihli E-81514179-100-120219 sayılı Tasarruf Mevduatı Sigorta Fonu İştirakler\nve Gayrimenkuller Daire Başkanlığı Mahkeme Kararı\nKayyım (Yönetim Kurulu/Yetkililer)\nYönetim Kurulu Üyeliğine Seçilenler\nTürkiye Cumhuriyeti Uyruklu 456******94 Kimlik No'lu, İstanbul/ATAŞEHİR adresinde\nikamet eden, ENİS GÜÇLÜ ŞİRİN Yönetim Kurulu Başkanı (Kayyım) olarak atanmıştır.\nTürkiye Cumhuriyeti Uyruklu 439******04 Kimlik No'lu, İstanbul/KUÜÇÜKÇEKMECE\nadresinde ikamet eden, ABDULKADİR KOÇAK Yönetim Kurulu Başkan Vekili (Kayyım)\nolarak atanmıştır. Türkiye Cumhuriyeti Uyruklu |24g##vx**3) Kımlık No'lu,\nİstanbul//ATAŞEHİR adresinde ikamet eden, REYHAN ŞENEL Yönetim Kurulu Üyesi\n(Kayyım) olarak atanmıştır. Türkiye Cumhuriyeti Uyruklu 378******60 Kımlık No'lu,\nİstanbul/Üsküdar adresinde ikamet eden, NACİT HAMİ OKTAY Yönetim Kurulu Üyesi\n(Kayyım) olarak atanmıştır. Türkiye Cumhuriyeti Uyruklu 181*****02 Kımlık No'lu,\nİstanbul//KARTAL adresinde ikamet eden, NURSEMİN GÜNGÖR Yönetim Kurulu Üyesi\n(Kayyım) olarak atanmıştır. Türkiye Cumhuriyeti Uyruklu 179******4) Kımlık No'lu,\nİstanbul/Üsküdar adresinde ikamet eden, SERAP GÜNAYDIN Yönetim Kurulu Üyesi\n(Kayyım) olarak atanmıştır. Türkiye Cumhuriyeti Uyruklu 326******572 Kımlık No'lu,\nİstanbul/Üsküdar adresinde ikamet eden, GÜLSEN ALTINSOY GÜNDOĞDU Yönetim\nKurulu Üyesi (Kayyım) olarak atanmıştır. Türkiye Cumhuriyeti Uyruklu 103******16\nKimlik No'lu, İstanbul//BAKIRKÖY adresinde ikamet eden, ERTUĞRUL SALICI Yönetim\nKurulu Üyesi (Kayyım) olarak atanmıştır. Türkiye Cumhuriyeti Uyruklu 306******88\n(Devamı 96. Sayfada)\n(Baştarafı 95 Sayfada)\nKimlik No'lu, İstanbul//BEYLİKDÜZÜ adresinde ikamet eden, SİNAN AKTAŞ Yönetim\nKurulu Üyesi (Kayyım) olarak atanmıştır. Türkiye Cumhuriyeti Uyruklu 226******84\nKimlik No'lu, İstanbul/BAŞAKŞEHİR adresinde ikamet eden, METİN ŞAPÇI Yönetim\nKurulu Üyesi (Kayyım) olarak atanmıştır. Türkiye Cumhuriyeti Uyruklu 475******7)\nKimlik No'lu, İstanbul/ÜMRANİYE adresinde ikamet eden, ERCAN DOĞAN Yönetim\nKurulu Üyesi (Kayyım) olarak atanmıştır. Türkiye Cumhuriyeti Uyruklu 187******90\nKimlik No'lu, İstanbul/SANCAKTEPE adresinde ikamet eden, EMRE ERTAŞ Yönetim\nKurulu Üyesi (Kayyım) olarak atanmıştır. Türkiye Cumhuriyeti Uyruklu 155******10\nKimlik No'lu, İstanbul/Üsküdar adresinde ikamet eden, SAMİ ERDEM Yönetim Kurulu\nÜyesi (Kayyım) olarak atanmıştır. Türkiye Cumhuriyeti Uyruklu 577******372 Kimlik\nNo'lu, İstanbul//KÜÇÜKÇEKMECE adresinde ikamet eden, SELMA YILDIZ Yönetim\nKurulu Üyesi (Kayyım) olarak atanmıştır. Türkiye Cumhuriyeti Uyruklu 227******3)\nKimlik No'lu, İstanbul//MALTEPE adresinde ikamet eden, DAVUT YILMAZ Yönetim\nKurulu Üyesi (Kayyım) olarak atanmıştır. Türkiye Cumhuriyeti Uyruklu 442******66\nKimlik No'lu, İstanbul/ŞİŞLİ adresinde ikamet eden, SÜMEYYE MUTLU Yönetim Kurulu\nÜyesi (Kayyım) olarak atanmıştır. Türkiye Cumhuriyeti Uyruklu 204******60 Kimlik\nNo'lu, İstanbul/KÜÇÜKÇEKMECE adresinde ikamet eden MURAT KARAKAYA\nYY TT\nx1oncüm Kululu Uyesi (Kayyım) Olarak alanmışlır. l1uyikiye umnuriycli UYyTuklu\n210******58 Kimlik No'lu, İstanbu/ÇEKMEKÖY adresinde ikamet eden, AYBİKE\nKAYNAR BARDAKCI Yönetim Kurulu Üyesi (Kayyım) olarak atanmıştır.\nTemsil Yetki Görevi Verilenler\nTürkiye Cumhuriyeti Uyruklu 456******94 Kimlik No'lu, İstanbul//ATAŞEHİR adresinde\nikamet eden, ENİS GÜÇLÜ ŞİRİN - Kayyım olarak atanmıştır.\nYetki Şekli: (ABDULKADİR KOÇAK, AYBİKE KAYNAR BARDAKCI, DAVUT\nYILMAZ, EMRE ERTAŞ, ERCAN DOĞAN, ERTUĞRUL SALICI, GÜLSEN\nALTINSOY GÜNDOĞDU, METİN ŞAPÇI, MURAT KARAKAYA, NACİT HAMİ\nOKTAY, NURSEMİN GÜNGÖR, REYHAN ŞENEL, SAMİ ERDEM, SELMA YILDIZ,\nSERAP GÜNAYDIN, SİNAN AKTAŞ, SÜMEYYE MUTLU) 'den Herhangi Birisiyle\nMüştereken Temsile Yetkilidir.\nTürkiye Cumhuriyeti Uyruklu 439******04 Kimlik No'lu, İstanbul/KÜÇÜKÇEKMECE\nadresinde ikamet eden, ABDULKADİR KOÇAK - Kayyım olarak atanmıştır.\nYetki Şekli: (AYBİKE KAYNAR BARDAKCI, DAVUT YILMAZ, EMRE ERTAŞ, ENİS\nGÜÇLÜ ŞİRİN, ERCAN DOĞAN, ERTUĞRUL SALICI, GÜLSEN ALTINSOY\nGÜNDOĞDU, METİN ŞAPÇI, MURAT KARAKAYA, NACİT HAMİ OKTAY,\nNURSEMİN GÜNGÖR, REYHAN ŞENEL, SAMİ ERDEM, SELMA YILDIZ, SERAP\nGÜNAYDIN, SİNAN AKTAŞ, SÜMEYYE MUTLU) 'den Herhangi Birisiyle Müştereken\nTemsile Yetkilidir.\nTürkiye Cumhuriyeti Uyruklu 124******87 Kimlik No'lu, İstanbul//ATAŞEHİR adresinde\nikamet eden, REYHAN ŞENEL - Kayyım olarak atanmıştır.\nYetki Şekli: (ABDULKADİR KOÇAK, AYBİKE KAYNAR BARDAKCI, DAVUT\nYILMAZ, EMRE ERTAŞ, ENİS GÜÇLÜ ŞİRİN, ERCAN DOĞAN, ERTUĞRUL\nSALICI, GÜLSEN ALTINSOY GÜNDOĞDU, METİN ŞAPÇI, MURAT KARAKAYA,\nNACİT HAMİ OKTAY, NURSEMİN GÜNGÖR, SAMİ ERDEM, SELMA YILDIZ,\nSERAP GÜNAYDIN, SİNAN AKTAŞ, SÜMEYYE MUTLU) 'den Herhangi Birisiyle\nMüştereken Temsile Yetkilidir.\nTürkiye Cumhuriyeti Uyruklu 378******60 Kimlik No'lu, İstanbul/Üsküdar adresinde\nikamet eden, NACİT HAMİ OKTAY - Kayyım olarak atanmıştır.\nYetki Şekli: (ABDULKADİR KOÇAK, AYBİKE KAYNAR BARDAKCI, DAVUT\nYILMAZ, EMRE ERTAŞ, ENİS GÜÇLÜ ŞİRİN, ERCAN DOĞAN, ERTUĞRUL\nSALICI, GÜLSEN ALTINSOY GÜNDOĞDU, METİN ŞAPÇI, MURAT KARAKAYA,\nNURSEMİN GÜNGÖR, REYHAN ŞENEL, SAMİ ERDEM, SELMA YILDIZ, SERAP\nGÜNAYDIN, SİNAN AKTAŞ, SÜMEYYE MUTLU) 'den Herhangi Birisiyle Müştereken\nTemsile Yetkilidir.\nTürkiye Cumhuriyeti Uyruklu 181******02 Kimlik No'lu, İstanbul/KARTAL adresinde\nikamet eden, NURSEMİN GÜNGÖR - Kayyım olarak atanmıştır.\nYetki Şekli: (ABDULKADİR KOÇAK, AYBİKE KAYNAR BARDAKCI, DAVUT\nYILMAZ, EMRE ERTAŞ, ENİS GÜÇLÜ ŞİRİN, ERCAN DOĞAN, ERTUĞRUL\nSALICI, GÜLSEN ALTINSOY GÜNDOĞDU, METİN ŞAPÇI, MURAT KARAKAYA,\nNACİT HAMİ OKTAY, REYHAN ŞENEL, SAMİ ERDEM, SELMA YILDIZ, SERAP\nGÜNAYDIN, SİNAN AKTAŞ, SÜMEYYE MUTLU) 'den Herhangi Birisiyle Müştereken\nTemsile Yetkilidir.\nTürkiye Cumhuriyeti Uyruklu 179******47 Kimlik No'lu, İstanbul/Üsküdar adresinde\nikamet eden. SERAP GÜNAYDIN - Kayyım olarak atanmıstır.\nYetki Şekli: (ABDULKADİR KOÇAK, AYBİKE KAYNAR BARDAKCI, DAVUT\nYILMAZ, EMRE ERTAŞ, ENİS GÜÇLÜ ŞİRİN, ERCAN DOĞAN, ERTUĞRUL\nSALICI, MURAT KARAKAYA, METİN ŞAPÇI, NACİT HAMİ OKTAY, NURSEMİN\nGÜNGÖR, REYHAN ŞENEL, SAMİ ERDEM, SELMA YILDIZ, SİNAN AKTAŞ,\nSÜMEYYE MUTLU) 'den Herhangi Birisiyle Müştereken Temsile Yetkilidir.\nTürkiye Cumhuriyeti Uyruklu 326******57 Kimlik No'lu, İstanbul/Üsküdar adresinde\nikamet eden, GÜLSEN ALTINSOY GÜNDOĞDU - Kayyım olarak atanmıştır.\nYetki Şekli: (ABDULKADİR KOÇAK, AYBİKE KAYNAR BARDAKCI, DAVUT\nYILMAZ, EMRE ERTAŞ, ENİS GÜÇLÜ ŞİRİN, ERCAN DOĞAN, ERTUĞRUL\nSALICI, METİN ŞAPÇI, MURAT KARAKAYA, NACİT HAMİ OKTAY, NURSEMİN\nGÜNGÖR, REYHAN ŞENEL, SAMİ ERDEM, SELMA YILDIZ, SERAP GÜNAYDIN,\nSİNAN AKTAŞ, SÜMEYYE MUTLU) 'den Herhangi Birisiyle Müştereken Temsile\nYetkilidir.\nTürkiye Cumhuriyeti Uyruklu 103******16 Kimlik No'lu, İstanbul//BAKIRKÖY adresinde\nikamet eden, ERTUĞRUL SALICI - Kayyım olarak atanmıştır.\nYetki Şekli: (ABDULKADİR KOÇAK, AYBİKE KAYNAR BARDAKCI, DAVUT\nYILMAZ, EMRE ERTAŞ, ENİS GÜÇLÜ ŞİRİN, ERCAN DOĞAN, GÜLSEN\nALTINSOY GÜNDOĞDU, METİN ŞAPÇI, MURAT KARAKAYA, NACİT HAMİ\nOKTAY, NURSEMİN GÜNGÖR, REYHAN ŞENEL, SAMİ ERDEM, SELMA YILDIZ,\nSERAP GÜNAYDIN, SİNAN AKTAŞ, SÜMEYYE MUTLU) 'den Herhangi Birisiyle\nMüştereken Temsile Yetkilidir.\nTürkiye Cumhuriyeti Uyruklu 306******88 Kimlik No'lu, İstanbul//BEYLİKDÜZÜ\nadresinde ikamet eden, SİNAN AKTAŞ - Kayyım olarak atanmıştır.\nYetki Şekli: (ABDULKADİR KOÇAK, AYBİKE KAYNAR BARDAKCI, DAVUT\nYILMAZ, EMRE ERTAŞ, ENİS GÜÇLÜ ŞİRİN, ERCAN DOĞAN, ERTUĞRUL\nSALICI, GÜLSEN ALTINSOY GÜNDOĞDU, METİN ŞAPÇI, MURAT KARAKAYA,\nNACİT HAMİ OKTAY, NURSEMİN GÜNGÖR, REYHAN ŞENEL, SAMİ ERDEM,\nSELMA YILDIZ, SERAP GÜNAYDIN, SÜMEYYE MUTLU) 'den Herhangi Birisiyle\nMüştereken Temsıle Yetkilidir. Türkiye Cumhuriyeti Uyruklu 226******834 Kımlık No'lu,\nİstanbul/BAŞAKŞEHİR adresinde ikamet eden, METİN ŞAPÇI - Kayyım olarak\natanmıştır. Yetki Şekli: (ABDULKADİR KOÇAK, AYBİKE KAYNAR BARDAKCI,\nDAVUT YILMAZ, EMRE ERTAŞ, ENİS GÜÇLÜ ŞİRİN, ERCAN DOĞAN,\nERTUĞRUL SALICI, GÜLSEN ALTINSOY GÜNDOĞDU, MURAT KARAKAYA,\nNACİT HAMİ OKTAY, NURSEMİN GÜNGÖR, REYHAN ŞENEL, SAMİ ERDEM,\nSELMA YILDIZ, SERAP GÜNAYDIN, SİNAN AKTAŞ, SÜMEYYE MUTLU) 'den\nHerhangı Birisiyle Müştereken Temsile Yetkilidir.. Türkiye Cumhuriyeti Uyruklu\n475*****X72 Kimlik No'lu, İstanbu/ÜUÜMRANİYE adresinde ikamet eden, ERCAN\nDOĞAN - Kayyım olarak atanmıştır. Yetki Şekli: (ABDULKADİR KOÇAK, AYBİKE\nKAYNAR BARDAKCI, DAVUT YILMAZ, EMRE ERTAŞ, ENİS GÜÇLÜ ŞİRİN,\nERTUĞRUL SALICI, GÜLSEN ALTINSOY GÜNDOĞDU, METİN ŞAPÇI, MURAT\nKARAKAYA, NACİT HAMİ OKTAY, NURSEMİN GÜNGÖR, REYHAN ŞENEL,\nSAMİ ERDEM, SELMA YILDIZ, SERAP GÜNAYDIN, SİNAN AKTAŞ, SÜMEYYE\nMUTLU) 'den Herhangi Birisiyle Müştereken Temsile Yetkilidir. Türkiye Cumhuriyeti\nUyruklu 187******90 Kimlik No'lu, İstanbul/SANCAKTEPE adresinde ikamet eden,\nEMRE ERTAŞ - Kayyım olarak atanmıştır. Yetki Şekli (ABDULKADİR KOÇAK,\nAYBİKE KAYNAR BARDAKCI, DAVUT YILMAZ, ENİS GÜÇLÜ ŞİRİN, ERCAN\nDOĞAN, ERTUĞRUL SALICI, GÜLSEN ALTINSOY GÜNDOĞDU, METİN ŞAPÇI,\nMURAT KARAKAYA, NACİT HAMİ OKTAY, NURSEMİN GÜNGÖR, REYHAN\nŞENEL, SAMİ ERDEM, SELMA YILDIZ, SERAP GÜNAYDIN, SİNAN AKTAŞ,\nSÜMEYYE MUTLU) 'den Herhangi Birisiyle Müştereken Temsile Yetkilidir. Türkiye\nCumhuriyeti Uyruklu 155******10 Kimlik No'lu, İstanbul/Üsküdar adresinde ikamet eden,\nSAMİ ERDEM - Kayyım olarak atanmıştır. Yetki Şekli: (ABDULKADİR KOÇAK,\nAYBİKE KAYNAR BARDAKCI, DAVUT YILMAZ, EMRE ERTAŞ, ENİS GÜÇLÜ\nŞİRİN, ERCAN DOĞAN, ERTUĞRUL SALICI, GÜLSEN ALTINSOY GÜNDOĞDU,\nMETİN ŞAPÇI, MURAT KARAKAYA, NACİT HAMİ OKTAY, NURSEMİN\nGÜNGÖR, REYHAN ŞENEL, SELMA YILDIZ, SERAP GÜNAYDIN, SİNAN AKTAŞ,\nSÜMEYYE MUTLU) 'den Herhangi Birisiyle Müştereken Temsile Yetkilidir. Türkiye\nCumhuriyeti Uyruklu 577******32 Kimlik No'lu, İstanbul KÜÇÜKÇEKMECE adresinde\nikamet eden, SELMA YILDIZ - Kayyım olarak atanmıştır. Yetki Şekli: (ABDULKADİR\nKOÇAK, AYBİKE KAYNAR BARDAKCI, DAVUT YILMAZ, EMRE ERTAŞ, ENİS\nGÜÇLÜ ŞİRİN, ERCAN DOĞAN, ERTUĞRUL SALICI, GÜLSEN ALTINSOY\nGÜNDOĞDU, METİN ŞAPÇI, MURAT KARAKAYA, NACİT HAMİ OKTAY,\nNURSEMİN GÜNGÖR, REYHAN ŞENEL, SAMİ ERDEM, SERAP GÜNAYDIN,\nSİNAN AKTAŞ, SÜMEYYE MUTLU) 'den Herhangi Birisiyle Müştereken Temsile\nYetkilidir. Türkiye Cumhuriyeti Uyruklu 227******32 Kimlik No'lu, İstanbul//MALTEPE\nadresinde ikamet eden, DAVUT YILMAZ - Kayyım olarak atanmıştır. Yetki Şekli:\n(ABDULKADİR KOÇAK, AYBİKE KAYNAR BARDAKCI, EMRE ERTAŞ, ENİS\nGÜÇLÜ ŞİRİN, ERCAN DOĞAN, ERTUĞRUL SALICI, GÜLSEN ALTINSOY\nGÜNDOĞDU, METİN ŞAPÇI, MURAT KARAKAYA, NACİT HAMİ OKTAY,\nNURSEMİN GÜNGÖR, REYHAN ŞENEL, SAMİ ERDEM, SELMA YILDIZ, SERAP\nGÜNAYDIN, SİNAN AKTAŞ, SÜMEYYE MUTLU) 'den Herhangi Birisiyle Müştereken\nTemsile Yetkilidir... Türkiye Cumhuriyeti Uyruklu 442******66 Kimlik No'lu,\nİstanbul/ŞİŞLİ adresinde ikamet eden, SÜMEYYE MUTLU - Kayyım olarak atanmıştır.\nYetki Şekli: (ABDULKADİR KOÇAK, AYBİKE KAYNAR BARDAKCI, DAVUT\nYILMAZ, EMRE ERTAŞ, ENİS GÜÇLÜ ŞİRİN, ERCAN DOĞAN, ERTUĞRUL\nSALICI, GÜLSEN ALTINSOY GÜNDOĞDU, METİN ŞAPÇI, MURAT KARAKAYA,\nNACİT HAMİ OKTAY, NURSEMİN GÜNGÖR, REYHAN ŞENEL, SAMİ ERDEM,\nSELMA YILDIZ, SERAP GÜNAYDIN, SİNAN AKTAŞ) 'den Herhangi Birisiyle\nMüştereken Temsıle Yetkilidir. Türkiye Cumhuriyeti Uyruklu 204****60 Kımlık No'lu,\nİstanbul//KÜÇÜKÇEKMECE adresinde ikamet eden, MURAT KARAKAYA - Kayyım\nolarak atanmıştır. Yetki Şekli (ABDULKADİR KOÇAK, AYBİKE KAYNAR\nBARDAKCI, DAVUT YILMAZ, EMRE ERTAŞ, ENİS GÜÇLÜ ŞİRİN, ERCAN\nDOĞAN, ERTUĞRUL SALICI, GÜLSEN ALTINSOY GÜNDOĞDU, METİN ŞAPÇI,\nNACİT HAMİ OKTAY, NURSEMİN GÜNGÖR, REYHAN ŞENEL, SAMİ ERDEM,\nSELMA YILDIZ, SERAP GÜNAYDIN, SİNAN AKTAŞ, SÜMEYYE MUTLU) 'den\nHerhangı Birisiyle Müştereken Temsile Yetkilidir.. Türkiye Cumhuriyeti Uyruklu\n210******58 Kimlik No'lu, İstanbul/ÇEKMEKÖY adresinde ikamet eden, AYBİKE\nKAYNAR BARDAKCI - Kayyım olarak atanmıştır. Yetki Şekli: (ABDULKADİR\nKOÇAK, DAVUT YILMAZ, EMRE ERTAŞ, ENİS GÜÇLÜ ŞİRİN, ERCAN DOĞAN,\nERTUĞRUL SALICI, GÜLSEN ALTINSOY GÜNDOĞDU, METİN ŞAPÇI, MURAT\nKARAKAYA, NACİT HAMİ OKTAY, NURSEMİN GÜNGÖR, REYHAN ŞENEL,\nSAMİ ERDEM, SELMA YILDIZ, SERAP GÜNAYDIN, SİNAN AKTAŞ, SÜMEYYE\nMUTLU) den Herhangı Bırısıyle Müştereken lemsıle Yetkilidir.",
  "box_id": "19994376"
}