{
  "mudurluk": "İstanbul",
  "ilan_sira_no": "51934",
  "mersis_no": null,
  "sicil_no": "212092",
  "ticaret_unvani": "VAKIF KATILIM BANKASI ANONIM ŞIRKETİ ANADOLU KURUMSAL SUBESI",
  "adres": "Kısıklı Mahallesi Kısıklı Cad. No: 105/2 Üsküdar/İstanbul",
  "metin": "Yukarıda bilgileri verilen şube ile ılgılı olarak aşağıda belirtilen hususlar müdürlüğümüze\nıbraz edilen belgelere ıstınaden ve Türk Ticaret Kanunu'na uygun olarak 28.2.2025\ntarihinde tescil edildiği ılan olunur.\nTescil Edilen Hususlar: Yetkililer\nTescile Delil Olan Belgeler:Üsküdar 32.noterliği' Nin 18.2.2025 Tarih 4866 Sayı İle\nTasdıklı, 7.2.2025 Tarıhlı 1926 Sayılı Yönetim Kurulu Kararı\nYETKİLİLER\nYENİ ATANAN TEMSİLCİLER\nTürkiye Cumhuriyeti Uyruklu 222******36 Kimlik No'lu, İSTANBUL / SULTANBEYLİ\nadresinde ikamet eden, HİDAYET ÇOBAN; Aksi Karar Alınıncaya Kadar (1. Derece İmza\nYetkilisi) Temsile Yetkili olarak seçilmiştir.Yetki Şekli: Sınırlı Yetkili (TTSG'de\nyayınlanmış 12.12.2017 tarihli ve 9471 sayılı İç Yönergede Belirtilen Şekilde\nYetkilendirilmiştir. )\nGÖREV DAĞILIMINDAKİ DEĞİŞİKLİK\nDaha önceden (1.Derece İmza Yetkilisi) Temsile Yetkili görevi olan Türkiye Cumhuriyeti\nUyruklu 150******86 Kimlik No'lu İSTANBUL / ÜSKÜDAR adresinde ikamet eden\nHAYRETTİN ŞAHİN'in önceki bu görevi sona ermiştir.\nMÜŞTEREK LİSTESİNDE DEĞİŞİKLİK\nTürkiye Cumhuriyeti Uyruklu 625******37 Kimlik No'lu, İSTANBUL / ÜMRANİYE\nadresinde ikamet eden, FEHMİ KAŞIKÇI için müşterek olduğu yetkililer ( FARUK ANIL\nSARICAOĞLU, SERKAN EKİN, UĞUR YURTSEVER, HİDAYET ÇOBAN ) şeklinde\ndeğıştırılmıştır.",
  "box_id": "19996750"
}