{
  "mudurluk": "İstanbul",
  "ilan_sira_no": "71795",
  "mersis_no": "0772065290626158",
  "sicil_no": "874993",
  "ticaret_unvani": "SIYER DIŞ TICARET ANONIM ŞIRKETİ",
  "adres": "Cumhuriyet Mah.1988 Sk.Papatya Residence Plaza N.4 K.2 D.17 Esenyurt/İstanbul",
  "metin": "Yukarıda bilgileri verilen şirket ile ılgılı olarak aşağıda belirtilen hususlar müdürlüğümüze\nıbraz edilen belgelere istinaden ve Türk Ticaret Kanunu'na uygun olarak 25.3.2025\ntarıhınde tescil edildiği ilan olunur.\nTescil Edilen Hususlar: Yönetim Kurulu / Yetkililer\nTescile Delil Olan Belgeler: Bakırköy 37. Noterliği' Nin 24.3.2025 Tarih 11940 Sayı İle\nTasdıklı, 12.3.2025 Tarıhli Genel Kurul Kararı Bakırköy 37. Noterliği' Nin 14.3.2025 Tarıh\n10767 Sayı İle Tasdikli, 13.3.2025 Tarihli 2025/02 Sayılı Yönetim Kurulu Kararı\nYÖNETİM KURULU / YETKİLİLER\nTürkiye (o Cumhuriyeti (oOUyruklu 584******58 Kimlik No'lu, İSTANBUL /\nBÜYÜKÇEKMECE adresinde ikamet eden, MUHİTTİN MEDAYİN EROL 12.3.2028\ntarihine kadar Yönetim Kurulu Üyesi olarak seçilmiştir.\nTürkiye (o Cumhuriyeti (oOUyruklu 584******58 Kimlik No'lu, İSTANBUL /\nBÜYÜKÇEKMECE adresinde ikamet eden, MUHİTTİN MEDAYİN EROL; 12.3.2028\ntarıhine kadar Yönetim Kurulu Başkanı olarak seçilmiştir.\nYENİ ATANAN TEMSİLCİLER\nTürkiye (o Cumhuriyeti (oOUyruklu 584******58 Kimlik No'lu, İSTANBUL /\nBÜYÜKÇEKMECE adresinde ikamet eden, MUHİTTİN MEDAYİN EROL; 12.3.2028\ntarihine kadar (YÖNETİM KURULU ÜYESİ) Temsile Yetkili olarak seçilmiştir. Yetki\nŞekli: Münferiden Temsıle Yetkilidir.\nTEMSİL YETKİSİ SONA ERENLER\nDaha önceden Yönetim Kurulu Başkanı görevi olan Türkiye Cumhuriyeti Uyruklu\n584******58 Kimlik No'lu İSTANBUL / BÜYÜKÇEKMECE adresinde ikamet eden\nMUHİTTİN MEDAYİN EROL'in önceki bu görevi sona ermiştir.",
  "box_id": "20058053"
}