{
  "mudurluk": "Kocaeli̇",
  "ilan_sira_no": "1298",
  "mersis_no": "0582112413100001",
  "sicil_no": "38370",
  "ticaret_unvani": "KOZA SAGLIK VE EGITIM HIZMETLERİ SANAYI VE TICARET LIMITED SIRKETİ",
  "adres": "Yahyakaptan Mah. Bestekar Amir Ateş Cad. No: 29a İzmit / Kocaeli",
  "metin": "Yukarıda bilgileri verilen şirket ile ılgılı olarak aşağıda belirtilen hususlar müdürlüğümüze\nıbraz edilen belgelere istinaden ve Türk Ticaret Kanunu'na uygun olarak 3.3.2025 tarihinde\ntescil edildiği ilan olunur.\nTescil Edilen Hususlar:Kuruluş\nTescile Delil Olan Belgeler:Şirket Sözleşmesi Kocaeli Ticaret Sicili Müdürlüğü\nHuzurunda 3.3.2025 Tarihinde İmzalanmıştır.\n1. Kuruluş\nAşağıdakı adları, soyadları, unvanları, yerleşim yerleri ve uyrukları yazılı kurucular\narasında bir Limited Şirket kurulmuş bulunmaktadır.\n2. ŞİRKETİN UNVANI a, j j j\nŞirketin unvanı KOZA SAĞLIK VE EĞİTİM HİZMETLERİ SANAYİ VE TİCARET\nLİMİTED ŞİRKET İdir.\n3. AMAÇ VE KONU\nI-İnsanların ve kurumların gelişimleri ile ilgili eğitim ve danışmanlık hizmetleri vermek.\nKişisel ve kurumsal gelişimlere yönelik eğitim destek seminerleri, kurslar ve başarı\nsınavları düzenlemek.\n2-Diş hekimleri, doktorlar ve diğer teknik personellerm mesleki bilgi ve tecrübelerini\narttırmak için konferanslar düzenlemek, yurtiçinde ve yurtdışında seminer çalışmaları\nyapmak.\n3-İnsan sağlığı ile ilgili her türlü hizmetler vermek.\n4-Türkiye'de modem tıp ve sağlık hizmetlerinin; bütün uzmanlık alanları ve branşlarda\nçağdaş ve son sistem cihazlarla donatılmış olan yataklı veya yataksız tesislerde merkezi ve\nseyyar araçlar kullanmak sureti ile gerekli yerlerden gerekli izinler alınarak yapılması,\n5-Her türlü tıp ve sağlık hizmetlerinin yapılabilmesi ıçın her türlü muayenehane, klınık,\nözel sağlık kurtları, özel poliklinikler, özel check-up merkezleri, laboratuar, tıp merkezi,\nOoze! Naslane, dnicnme evicri yapılması ve gerci Iziniciim geickli yerlerden alınması VE\nişletilmesi,\n6-Tıp ve sağlık hizmetlerinin yapılabilmesi ıçın her türlü sarf ve ihtiyaç maddelerinin,\nperaparat ve ilaçların, her türlü kımyasal, organık ve inorganık maddelerin imalı, alınıp\nsatılması, ıthal ve ihracı,\n7-Hastaların her türlü teşhis, tedavı, tedavı sonu bakımları ile rehabılıtasyonlarını sağlayıcı\nhizmetlerini yapmak,\n8-Ağız ve diş bakımını gerçekleştirmek, diş hekimliği yapmak, her türlü ağız ve dış\nhastalıklarının tedavı, cerrahı yönlerde teşhis ve tedavısının yapılması\n9-Sağlık sektörü tile Ilgili olarak hasta kabul etmek, teşhis, tedavı hizmetlermde bulunmak,\nlaboratuar ve benzeri tesisler kurmak, çeşitli kamu kurum ve kuruluşları ile özel sektöre ait\nkuruluşlarla anlaşma yaparak personellerine sağlık hizmetleri vermek,\n10-Şirketin doktor ve diğer teknik personelinin mesleki bilgi ve tecrübelerini arttırmak içın\nkonferanslar düzenleme, yurtiçmde ve yurtdışında seminer çalışmaları yapmak ve bu\nseminerlere katılmak\nI 1-Şirket işleri ıçın gerekli taşıtları almak, satmak, devretmek ve bunların üzerinde aynı ve\nşahsı tasarrufta bulunmak.\n12-Şirketin amacına ulaşabilmesi içın yurt içinden, yurt dışından her türlü krediler, emval\nkefalet kredileri, senet üzerine avans kredilerinin alınması, aracılık yapmak kaydı ile\nkullanılması;\n13-Şirketin konusu 1le ilgili her türlü gayrı menkuller, menkul mallar, şirket konusu 1le ilgili\nmotorlu kara nakıl vasıtaları ıle makine ve tesislerin alınması, satılması, kiraya verilmesi,\nkıraya alınması, gayrı menkuller üzerinde aracılık yapmamak kaydı ile her türlü aynı ve\nşahsı hakların tesis ve tecili, tasarrudarında bulunulması;\n14-Şirketin lüzumlu borç ve alacaklarını, kefalet ve teminatları ile alacağı kredilerin\nteminatının temin için şirketin lehinde veya aleyhinde olmak üzere borç Ipotekleri, alacak\nıpotekleri, teminat Ipotekleri, kefalet 1ıpotekleri alınması, verilmesi, her türlü teminat ve\nkefaletlerin verilmesi, alınması, ticari işletme rehini akdedilmesi;\n15-Şirketin konusu ile ilgili her türlü markaların, ihtira haklan ve beratlarının,\nruhsatnamelerin, ustalık haklarının, ticaret unvanlarının, brövelerin alınması, satılması,\nkıraya alınması, kiraya verilmesi,\n16-Gerek 6224 sayılı yabancı sermayeyi teşvik kanunu gerekse somadan çıkarılan kanun\nhükmünde karamame, yönetmelik hükümlerine göre şirketin faalıyet konularına giren işleri\nyapan gerçek ve tüzel kışıler ile şirket teşkili ortak girişimlerde bulunulması mevcut tıcarı\nişletmelere ıştırak edilmesi,\n17-Yurt içinde ve yurt dışındaki ağız ve diş sağlığı hizmetleri sunmak ve bu sektörün\nıhtıyacı olan makine, alet, cıhaz, malzeme, ham madde, yarı mamul madde, araç ve\ngereçleri ile hizmetleri almak, projelendirme, ımal etmek veya ettirmek maksat ve konuları\niçinde her türlü eğitim hizmetlermi ve müşavırlık çalışmalarını yapmak, hasta eğitimi,\nhekim eğitimi ve yönlendirmesi ile ılgılı hizmetleri yürütmek ve bu alanda kitaplar ve\nbroşürler hazırlamak, seminerler düzenlemek ve düzenlettirmek veya bunlarla ılgılı her\ntürlü dahılı ticarı ıthalı, ihracı vesaire bil cümle faaliyetlerle iştigal etmek.\n18-Dış teknisyenliğinde kullanılan her türlü laboratuvar cıhazı ve aletinin imalatı alım,\nsatım ve ticaretini yapmak.\n19-İştigal konusu ile ilgili olarak her türlü diş deposu malzemesinin ithalat ve ihracatını\nyapmak.\n20-Konusu 1le ılgılı diş protez, porselen ımalatı ıhracat ve Ithalat dahılı ticaret taahhüt işleri\nyapmak.\n21-Mesleki eğitim hizmetleri vermek.\n22-Konusu ile ılgılı olarak yerli ve yabancı firmalardan mümessillikler ve acentelikler alır,\nyerli ve yabancı firmalara acentelikler ve mümessillikler verilir.\n23-Dış protez laboratuvarı açmak ve işletmek.\n24-Her türlü ınşaat taahhüt işleri; konut, Işyeri, ticarethane inşaatlarını yapmak, satmak,\nkendi hesabına arazı ve arsalar almak ve bunlar üzerinde veya başkalarına ait arsa ve\narazıler üzerinde kat karşılığı binalar yapmak, satmak, kiraya vermek.\n25-Hava, kara, deniz nakıl vasıtaları ile şehir içi, şehirlerarası, milletler arası yolculuk ve\nyük taşımacılığı, işletmeciliği yapmak, oto vasıta sanayı ve Iş makinelerini kiralama işlerini\nyapmak.\n26-Soğuk hava depoları kurmak, satın almak, kiralamak, bunları işletmek veya kiraya\nvermek.\n27-0tomotiv sanayine ait her türlü ham madde, yardımcı madde, yarı mamul, mamul ve\nyedek parça aksam ve teferruatını alını, satım ve montajı ile 1thal ve ihracatını yapmak.\n28-Motorlu ve motorsuz kara, deniz, hava nakıl vasıtaları ve yedek parçaları ile diğer taşıt\naraçları ve parçalarının alım satım ıthal ıhraç ve pazarlamasını yapmak.\n29-Her türlü emlak ve oto alım satımı ve komısyonculuğunu yapmak.\n30-Her türlü hazır mobilya alım ve satımını yapmak.\n31-Her türlü makıne, teçhizat ve malzemelerinin alım ve satımını yapmak.\n32-Turizm, otelcilik, konaklama, restoran işletmeciliği, catering hizmetleri açmak, işletmek\nve kiralamak.\nBu maksat ve mevzu çerçevesinde olmak üzere şirket;\na-) Şirket konusu ile ilgili resmi özel ve tüzel kuruluşlarının ihalesine katılabilir, bununla\nılgili gerekli sözleşmeleri akdedebilir.\nb-) Şirketin faalıyet konusuna giren her malın mümessilliğini alır.\nc-) Teknik yardım 1le ılgılı anlaşmalar akdetmek ;\nd-) Gerekli teçhizat ve araçların satın alınması, kiralanması, ithalı ve ihracı ile iştigal\nedebilir. Şirket gerek maksadı gerekse başka hizmetleri yürütebilmesi ıçın gayrimenkuller\nsatın alabılır, satabılır ve kiraya verebilir.\ne-) Her türlü özel ve resmi satın alma komisyonlarına, ihalelere ıştırak eder, taahhütlerinde\nbulunur, taahhütler kabul eder.\n1-) Yatırım işletmecilik, ithalat, ihracat ve dahılı ticaret yapar.\ng-) Dahili ve harici istikraz sözleşmeleri akdeder.\n(Devamı 476. Sayfada)\n(Baştarafı 475 Sayfada)\nh-) Yurt içi ve yurt dışında kredi veren müesseselerde ve bankalarda her türlü kredi\nanlaşmaları yapar.\n1-) Borç ve alacaklarına teminat olarak, ipotek, rehin, kefalet ve teminatları alır, verir.\n1-) Her türlü ham, yarı mamul, mamul maddeler satın alır, ıthal eder, bunları kısmen ya da\ntamamen işledikten soma veya aynen satar, devreder ve bu maddeler üzerinde bilumum\nticari işlemlerde bulunur.\nJ-) Tesisler, atölyeler, fabrikalar kurar ınşa eder, bunları tevzılı ve tevdi ıçın gerekli her türlü\nmalzeme, makine ve cihazları yurt içimde ve yurt dışından, satın alır, satar, devralır,\ndevreder, kıralar.\nk-) Nakit vasıtası, menkul, gayrı menkul satın alır, satar, kiralar, kiraya verir, devralır,\ndevreder, nakit vasıtalarını işletir, gerek kendine gerekse üçüncü şahısların menkul ve\ngayrimenkulleri üzerinde şirket leh ve aleyhinde rehin ve ipotek dahıl olmak üzere her çeşit\naynı haklar ıktısap, tesis fek eder.\nm-) Yerli, yabancı, hakiki ve hükmi şahıs ve firmalardan temsilcilik, acentelik,\nmümessillik, distribütörlük verir, toptancılık, bayılık yapar.\nn-) Şirketi tanıtmaya yönelik ve konusu 1le ilgili broşürler basar ve yayınlar.\n4. ŞİRKETİN MERKEZİ\nŞirketin merkezi KOCAELİili İZMİT ilçesi'dir. Adresi YAHYAKAPTAN MAH.\nBESTEKAR AMİR ATEŞ CAD. NO: 29A İZMİT / KOCAELİ'dir.Adres değişikliğinde\nyeni adres, ticaret sıcılıne tescil ve Türkiye Ticaret Sicılı Gazetesi'nde Ilan ettirilir. Tescil ve\nılan edilmiş adrese yapılan tebligat şirkete yapılmış sayılır. Tescil ve ilan edilmiş\nadresinden ayrılmış olmasına rağmen, yeni adresini süresi içinde tescil ettirmemiş şirket\nıçın bu durum fesih sebebi sayılır.\n5. SÜRE\nŞirketin süresi, kuruluşundan itibaren sınırsız'dır. Bu süre şirket sözleşmesini değiştirmek\nsuretiyle uzatılıp kısaltılabilir.\n6. SERMAYE VE PAY SENETLERİNİN NEV'İ\nŞirketin sermayesi, beheri 1000,00 Türk Lirası değerinde 1020 paya ayrılmış toplam\n1020000,00 Türk Lirası değerindedir.\n-Beheri 1000,00 Türk Lirası değermde 170 adet paya karşılık gelen 17000000 Türk Lirası\nZEYNEP UZGUR tarafından nakdi,\n-Beheri 1000,00 Türk Lirası değermde 340 adet paya karşılık gelen 34000000 Türk Lirası\nMEHTAP EFE tarafından nakdi,\n-Beheri 1000,00 Türk Lirası değermde 340 adet paya karşılık gelen 34000000 Türk Lirası\nSUBRA İLHAN tarafından nakdi,\n-Beheri 1000,00 Türk Lirası değermde 170 adet paya karşılık gelen 17000000 Türk Lirası\nRECEP UZGUR tarafından nakdı, olarak taahhüt edilmiştir.\nNakden taahhüt edilen payların itibarı değerleri, şirketin tescilini izleyen 24 ay içinde\nödenecektir.\n7. ŞİRKETİN İDARESİ\nŞirketin işleri ve işlemleri genel kurul tarafından seçilecek bir veya birkaç müdür tarafından\nAksı Karar Alınıncaya Kadar Türkiye Cumhuriyeti Uyruklu 104*****X338 Kimlık No'lu,\nKOCAELİ / KARTEPE adresinde ikamet eden RECEP UZGUR Müdür olarak\nseçilmiştir. Yetki Şekli: Münferiden Temsile Yetkilidir.\n8. TEMSİL\nŞirketi müdürler temsıl ederler. Şirketi temsil edecek imzalar genel kurul tarafından tespit,\nm ve em\ntescili ve Han Olunur. Mudurler, ŞIKCi. nizmci akdi 11 Dagli Olanları sSiniili yelkiye sahıp\nticarı vekil veya diğer tacir yardımcıları olarak atayabılır. Bu şekilde atanacak olanların\ngörev ve yetkileri, hazırlanacak iç yönergede açıkça belirlenir. Bu durumda iç yönergenin\ntescil ve ilanı zorunludur. İç yönerge ile ticari vekil ve diğer tacir yardımcıları atanamaz.\nYetkilendirilen ticarı vekil veya diğer tacır yardımcıları da ticaret siciline tescil ve ilan\nedilir. Bu kişilerin, şirkete ve üçüncü kişilere verecekleri her tür zarardan dolayı müdürler\nmüteselsilen sorumludur.\n9. GENEL KURUL\nGenel Kurullar, olağan ve olağanüstü toplanırlar. Olağan genel kurul, her yıl hesap\ndöneminin sona ermesinden itibaren 3 ay içinde; olağanüstü genel kurullar ise, Şirket\nişlerinin gerektirdiği hallerde ve zamanlarda toplanır. Genel kurul toplantılarında, her\nortağın oy hakkı, esas sermaye paylarının itibarı değerine göre hesaplanır. Genel kurul\ntoplantıları ve bu toplantılardakı karar nisabı, Türk Ticaret Kanunu hükümlerine tabidir.\nGenel kurul, şirketin merkez adresinde veya yönetim merkezinin bulunduğu şehrin elverişli\nbir yerinde toplanır.\n10. İLAN\nGenel kurulun toplantıya çağrılmasına ilişkin ilanlar da dahıl olmak üzere Şirkete ait ilanlar\nTürkiye Ticaret Sıcılı Gazetesinde yapılır. Genel kurul toplantılarına ılışkın ilanların\ntoplantı gününden en az on gün önce yapılması zorunludur.\n11. HESAP DÖNEMİ\nŞirketin hesap yılı, Ocak ayının 1. gününden başlar ve Aralık ayının 31. günü sona erer.\nFakat birinci hesap yılı, Şirketin kesin olarak kurulduğu tarihten ıtıbaren başlar ve o senenin\naralık ayının otuz birinci günü sona erer.\n12. KARIN TESPİTİ VE DAĞITIMI\nŞirketin net dönem karı yapılmış her çeşit masrafların çıkarılmasından sonra kalan\nmiktardır. Net dönem kârından her yıl 905 genel kanuni yedek akçe ayrılır; kalan miktar,\ngenel kurul kararı ile pay sahiplerine kar payı olarak dağıtılır. Kar payı, esas sermaye\npayının itibarı değerine, yerine getinlen ek ödeme yükümlülüğünün tutarı eklenmek\nsuretiyle oluşacak toplam mıktara oranla hesaplanır.\n13. YEDEK AKÇE\nYedek akçelerin ayrılması hususunda Türk Ticaret Kanununun 519 ila 523. maddeleri\nhükümleri uygulanır.\n14. KANUNİ HÜKÜMLER\nBu şirket sözleşmesinde bulunmayan hususlar hakkında Türk Ticaret Kanunu hükümleri\nuygulanır.\nKURUCULAR\n|",
  "box_id": "19997731"
}