{
  "mudurluk": "Karabük",
  "ilan_sira_no": "136",
  "mersis_no": "0456000468502919",
  "sicil_no": "835",
  "ticaret_unvani": "TURKIYE HALK BANKASI ANONIM SIRKETI KARABUK SUBESİ",
  "adres": "Bayır Mah. Kemal Güneş Cad. No: 116b Merkez / Karabük",
  "metin": "Yukarıda bilgileri verilen şube ile ilgili olarak aşağıda belirtilen hususlar müdürlüğümüze\nıbraz edilen belgelere istinaden ve Türk Ticaret Kanunu'na uygun olarak 3.3.2025 tarihinde\ntescil edildiği ilan olunur.\nTescil Edilen Hususlar: Yetkililer\nTescile Delil Olan Belgeler:1 1 2 2025 Tarıhlı 1397 Sayılı Diğer Kararı (Yetkili Makam )",
  "box_id": null
}