{
  "mudurluk": "İstanbul",
  "ilan_sira_no": "72395",
  "mersis_no": "0179161747200001",
  "sicil_no": "1075857",
  "ticaret_unvani": null,
  "adres": "Hürriyet Mah. Mahmutbey Cad. No: 17 İç Kapı No: 409 Bahçelievler / İstanbul",
  "metin": "Yukarıda bilgileri verilen şirket ile ılgılı olarak aşağıda belirtilen hususlar müdürlüğümüze\nıbraz edilen belgelere istmaden ve Türk Ticaret Kanunu'na uygun olarak 26.3.2025\ntarihinde tescil edildiği ilan olunur.\nTescil Edilen Hususlar:Kuruluş\n1. Kuruluş\nAşağıdaki adı, soyadı, unvanı, yerleşim yeri ve uyruğu yazılı kurucu tarafından bir Limited\nŞirket kurulmuş bulunmaktadır.\nççççeoo0000000000Oİ\n2. ŞİRKETİN UNVANI j j a, j j\nŞirketin unvanı BOFS TEKSTİL VE KİMYEVİ ÜRÜNLER LİMİTED ŞİRKET İdir.\n3. AMAÇ VE KONU\n-Endüstriyel kimyasalların toptan ticaretini yapmak .(anılın, matbaa mürekkebi, kımyasal\nyapıştırıcı, havai fişek, boyama maddeleri, sentetik reçine, metil alkol, parafin, esans ve\ntatlandırıcı, soda, sanayı tuzu, parafın, nıtrık asıt, amonyak, sanayı gazları vb.)\n-Tekstil ürünlerinin bir ücret veya sözleşmeye dayalı olarak toptan satışını yapmak .(ıplık,\nkumaş, ev tekstili, perde vb. ürünler) (giyim eşyaları hariç)\n4. ŞİRKETİN MERKEZİ\nŞirketin merkezi İSTANBULili BAHÇELİEVLERilçesi'dir. Adresi HÜRRİYET MAH.\nMAHMUTBEY CAD. NO: 17 İÇ KAPI NO: 409 BAHÇELİEVLER / İSTANBUL 'dir.\nAdres değişikliğinde yeni adres, ticaret siciline tescil ve Türkiye Ticaret Sıcılı Gazetesi'nde\nılan ettirilir. Tescil ve ilan edilmiş adrese yapılan tebligat şırkete yapılmış sayılır. Tescil ve\nılan edilmiş adresinden ayrılmış olmasına rağmen, yeni adresini süresi içinde tescil\nettirmemiş şirket ıçın bu durum fesih sebebi sayılır.\n5. SÜRE\nŞirketin süresi, kuruluşundan itibaren sınırsız'dır. Bu süre şirket sözleşmesini değiştirmek\nsuretiyle uzatılıp kısaltılabilir.\n6. SERMAYE VE PAY SENETLERİNİN NEW'İ\nŞirketin sermayesi, beheri 1000,00 Türk Lirası değerinde 1000 paya ayrılmış toplam\n1000000,00 Türk Lirası değerindedir.\n-Beheri 1000.00 Türk Lirası değerinde 1000 adet paya karşılık gelen 1000000,00 Türk\nLirası MUHAMMET DUMAN tarafından nakdı, olarak taahhüt edilmıştır.\nNakden taahhüt edilen payların itibarı değerleri, şirketin tescilini izleyen 24 ay içinde\nödenecektir.\n7. ŞİRKETİN İDARESİ\nŞirketin işleri ve işlemleri genel kurul tarafından seçilecek bir veya birkaç müdür tarafından\nAksı Karar Alınıncaya Kadar Türkiye Cumhuriyeti Uyruklu 583*****X08 Kımlık No'lu,\nİSTANBUL / BAYRAMPAŞA adresinde ikamet eden, MUHAMMET DUMAN Müdür\nolarak seçilmiştir. Yetki Şekli: Münferiden Temsile Yetkilidir.\n8. TEMSİL\nŞirketi müdürler temsil ederler. Şirketi temsil edecek imzalar genel kurul tarafından tespit,\ntescil ve ilan olunur. Müdürler, şirkete hizmet akdı ile bağlı olanları sınırlı yetkiye sahip\ntıcarı vekil veya diğer tacır yardımcıları olarak atayabilir. Bu şekilde atanacak olanların\ngörev ve yetkileri, hazırlanacak iç yönergede açıkça belirlenir. Bu durumda iç yönergenin\ntescil ve ilanı zorunludur. İç yönerge ile ticari vekil ve diğer tacir yardımcıları atanamaz.\nYetkilendinlen ticarı vekil veya diğer tacır yardımcıları da ticaret siciline tescil ve Ilan\nedilir. Bu kişilerin, şirkete ve üçüncü kişilere verecekleri her tür zarardan dolayı müdürler\nmüteselsilen sorumludur.\n9. GENEL KURUL\nGenel Kurullar, olağan ve olağanüstü toplanırlar. Olağan genel kurul, her yıl hesap\ndöneminin sona ermesinden itibaren 3 ay içinde; olağanüstü genel kurullar ise, Şirket\nişlerinin gerektirdiği hallerde ve zamanlarda toplanır. Genel kurul toplantılarında, her\nortağın oy hakkı, esas sermaye paylarının itibarı değerine göre hesaplanır. Genel kurul\ntoplantıları ve bu toplantılardakı karar nisabı, Türk Ticaret Kanunu hükümlerme tabıdır.\nGenel kurul, şirketin merkez adresinde veya yönetim merkezinin bulunduğu şehrin elverişli\nbir yerinde toplanır.\n10. İLAN\nGenel kurulun toplantıya çağrılmasına ılışkın ilanlar da dahil olmak üzere Şirkete att ilanlar\nTürkiye Ticaret Sıcılı Gazetesinde yapılır. Genel kurul toplantılarma ılişkın ilanların\ntoplantı gününden en az on gün önce yapılması zorunludur.\n11. HESAP DÖNEMİ\nŞirketin hesap yılı, Ocak ayının |. gününden başlar ve Aralık ayının 31. günü sona erer.\nFakat birinci hesap yılı, Şirketin kesin olarak kurulduğu tarihten itibaren başlar ve o senenin\naralık ayının otuz birinci günü sona erer.\n12. KARIN TESPİTİ VE DAĞITIMI\nŞirketin net dönem karı yapılmış her çeşit masrafların çıkarılmasından sonra kalan\nmıktardır. Net dönem kârından her yıl 965 genel kanuni yedek akçe ayrılır; kalan miktar,\ngenevi KUTU! Kalalı We Day sanıpıcııme Kar Dayi Olalak dagıllin. Sar Dayı, vsas selilayc\npayının itibari değerine, yerine getinlen ek ödeme yükümlülüğünün tutarı eklenmek\nsuretiyle oluşacak toplam mıktara oranla hesaplanır.\n13. YEDEK AKÇE\nYedek akçelerin ayrılması hususunda Türk Ticaret Kanununun 519 ıla 523. maddeleri\nhükümleri uygulanır.\n14. KANUNİ HÜKÜMLER\nBu şirket sözleşmesinde bulunmayan hususlar hakkında Türk Ticaret Kanunu hükümleri\nuygulanır.\nKURUCULAR",
  "box_id": "20059989"
}