{
  "mudurluk": "Sakarya",
  "ilan_sira_no": "1891",
  "mersis_no": "0745088351000002",
  "sicil_no": "29880",
  "ticaret_unvani": "SARFE UNLU MAMULLER GIDA MADDELERİ INŞAAT VE INŞAAT İl MALZEMELERI TURIZM SANAYI ANONIM ŞIRKETI PAMUKOVA ŞUBESİ",
  "adres": "Yenice Mahallesi Ergenekon Cad. No: 31/ Pamukova/Sakarya",
  "metin": "Yukarıda bilgileri verilen şube ile ilgili olarak aşağıda belirtilen hususlar müdürlüğümüze\nıbraz edilen belgelere istmaden ve Türk Ticaret Kanunu'na uygun olarak 26.3.2025\ntarihinde tescil edildiği ilan olunur.\nTescil Edilen Hususlar: Yetkililer\nTescile Delil Olan Belgeler:20 3 2025 Tarıhlı 2025/04 Sayılı Yönetim Kurulu Kararı\nYETKİLİLER\nYENİ ATANAN TEMSİLCİLER\nTürkiye Cumhuriyeti Uyruklu 199******18 Kimlik No'lu, İSTANBUL / KADIKÖY\nadresinde ikamet eden, KÜBRA CEREN KOÇLAR; Aksi Karar Alınıncaya Kadar Şube\nMüdürü olarak seçilmiştir. Yetki Şekli: Münferiden Temsile Yetkilidir.\nGÖREV DAĞILIMINDAKİ DEĞİŞİKLİK\nDaha önceden Şube Müdürü görevi olan Türkiye Cumhuriyeti Uyruklu 100*****x16\nKimlik No'lu SAKARYA / SERDİVAN adresinde ikamet eden SERDAR YILMAZ'ın\nönceki bu görevi sona ermiştir.",
  "box_id": "20060387"
}