{
  "mudurluk": "Antalya",
  "ilan_sira_no": "4101",
  "mersis_no": "0131170931700001",
  "sicil_no": "126123",
  "ticaret_unvani": "BAKA OTELCİLİK TURIZM INŞAAT EMLAK SANAYI VE TICARET LIMITED SIRKETİ",
  "adres": "Yüksekalan Mah. 546 Sk. Aslı Sitesi A Blok No: 2a İç Kapı No: K Muratpaşa / Antalya",
  "metin": "Yukarıda bilgileri verilen şirket ile ılgılı olarak aşağıda belirtilen hususlar müdürlüğümüze\nıbraz edilen belgelere istinaden ve Türk Ticaret Kanunu'na uygun olarak 3.3.2025 tarihinde\ntescil edildiği ilan olunur.\nTescil Edilen Hususlar:Pay Devri, Müdürler / Yetkililer\nTescile Delil Olan Belgeler:T.c. Antalya 5.noterliği Nin 3.3.2025 Tarih 04522 Sayı İle\nTasdikli, (Hisse Devri, Müdür İptal Atama Kararı),28.2.2025 Tarihli 2 Sayılı Genel Kurul\nKararı\nPAY DEVRİ\nPay Değişikliği\nŞirket Ortaklarından 195**»***58 Kımlık Numaralı ZAFER KAHYA 10.000,00 TL\nsermaye karşılığı 200 adet payını hukuki ve malı yükümlülükleri ile 105******38 Kimlik\nNumaralı MUSTAFA NOYAN'e devretmiştir.\nTek Ortaklık Bilgisi\nŞirket tek ortaklı bir Limited Şırkettir. Bu ortak, ANTALYA / AKSU adresinde ikamet\neden Türkiye Cumhuriyeti Uyruklu 10538 Kimlik Numaralı MUSTAFA NOYAN\n\"dir.\nGerçekleşen pay devrine bağlı olarak şirketin son ortaklık yapısı aşağıdaki gibidir:\nMUSTAFA NOYAN : Beheri 50,00 Türk Lirası değerinde 200 adet paya karşılık gelen\n10000,00 Türk Lirası\nMÜDÜRLER / YETKİLİLER\nMÜDÜRLÜĞE SEÇİLENLER\nTürkiye Cumhuriyeti Uyruklu 105******38 Kimlik No'lu, ANTALYA / AKSU adresinde\nIkamet eden, MUSTAFA NOYAN; Aksi Karar Alınıncaya Kadar Müdür olarak\nseçilmiştir. Yetki Şekli: Münferiden Temsile Yetkilidir.\nGÖREV DAĞILIMINDAKİ DEĞİŞİKLİK\nDaha önceden Müdür görevi olan Türkiye Cumhuriyeti Uyruklu 195******58 Kımlık\nNo'lu ANTALYA / MURATPAŞA adresinde Ikamet eden ZAFER KAHYA\"'ın önceki bu\ngörevi sona ermiştir.",
  "box_id": "19999623"
}