{
  "mudurluk": "Çorlu",
  "ilan_sira_no": "893",
  "mersis_no": "0396008744100013",
  "sicil_no": "4887",
  "ticaret_unvani": "ÖZ-EREN TURİZM İNŞAAT TAAHHÜT NALBURİYE HIRDAVAT SANAYİ VE TİCARET LİMİTED ŞİRKETİ",
  "adres": "Kemalettin Mah. Mersin Sk. No: 16a Çorlu / Tekirdağ",
  "metin": "Yukarıda bilgileri verilen şirket ile ılgılı olarak aşağıda belirtilen hususlar müdürlüğümüze\nıbraz edilen belgelere ıstınaden ve Türk Ticaret Kanunu'na uygun olarak 3.3.2025 tarihinde\ntescil edildiği ılan olunur.\nTescil Edilen Hususlar:Şırketin Merkezi\nTescile Delil Olan Belgeler:3.3.2025 Tarıhlı 2025/02 Sayılı Diğer Kararı, (T.c. Adalet\nBakanlığı Çorlu 3. Noterliği 03.03.2025 Tarih Ve 392 Yevmiye Numarası İle Tasdikli\nGenel Kurul Kararı)\nŞİRKETİN MERKEZİ\nMadde 4- Yukarıda bilgileri bulunan şirketin adresi KEMALETTİN MAH. KÜÇÜK\nÇAVUŞ MEYDANI METİN ER SOKAK NO:2 ÇORLU/TEKİRDAĞ adresinden,\nKEMALETTİN MAH. MERSİN SK. NO: 16A ÇORLU / TEKİRDAĞ adresine taşınmıştır.",
  "box_id": "19999644"
}