{
  "mudurluk": "Bursa",
  "ilan_sira_no": "4141",
  "mersis_no": "0191134482100001",
  "sicil_no": "75366",
  "ticaret_unvani": "BURTOM BURSA TIBBI ORGANIZASYON MERKEZLERI ANONIM ŞIRKETİ",
  "adres": "Minareliçavuş Bursa Osb Mah. Yeşil Cad. No: 2 Nilüfer / Bursa",
  "metin": "Yukarıda Bilgileri Verilen Şirket İle İlgili Olarak Aşağıda Belirtilen Hususlar\nMüdürlüğümüze İbraz Edilen Belgelere İstinaden Ve Türk Ticaret Kanunu'na Uygun\nOlarak 03.03.2025 Tarihinde Tescil Edilmeksizin İlan Olunur.\nTESCİL HARİCİ İLAN: PAY DEVRİ\nİLANA DELİL OLAN BELGELER: 25.2.2025 tarihli 2025/1 sayılı Yönetim Kurulu\nKararı\nŞirket pay sahiplerinden 389******72 Kimlik Numaralı ABİDİN SAĞLAM 10,00 TL\nsermaye karşılığı 10 adet payını hukuki ve mali yükümlülükleri ile 109******9) Kimlik\nNumaralı ASUMAN GÜRSOY TÜRKER'e devretmiştir.\nŞirket pay sahiplerinden 163******08 Kimlik Numaralı MEHMET AKİF EREN\nÇUHADAR 10,00 TL sermaye karşılığı 10 adet payını hukuki ve malı yükümlülükleri ile\n245******66 Kimlik Numaralı SERDAR ALP DEMİRTAŞ'e devretmiştir.\nŞirket pay sahiplerinden 263******06 Kimlik Numaralı İSMAİL HAKKI TEKKEŞİN\n10,00 TL sermaye karşılığı 10 adet payını hukuki ve malı yükümlülükleri ile 21406\nKimlik Numaralı AHMET TURGUT'e devretmiştir.\nŞirket pay sahiplerinden 356******74 Kımlık Numaralı KORAY BOYSAN 10.00 TL\nsermaye karşılığı 10 adet payını hukuki ve mali yükümlülükleri ile 378******08 Kimlik\nNumaralı EROL KILIÇ'e devretmiştir.",
  "box_id": "19999602"
}