{
  "mudurluk": "İstanbul",
  "ilan_sira_no": "72698",
  "mersis_no": "0080082094100001",
  "sicil_no": "215297",
  "ticaret_unvani": "MESUT MUTEAHHITLIK GAYRIMENKUL OTOMOTİV INŞAAT MALZEMELERİ LIMITED ŞIRKETİ Eski Ticaret Unvanı: İl | ARMES MOTORS OTOMOTİV INŞAAT SANAYI VE TICARET LIMITED SIRKETI",
  "adres": "Zübeyde Hanım Mah. 1269. Sk. No: 22 İç Kapı No: 6 Sultangazi / İstanbul",
  "metin": "Yukarıda bilgileri verilen şirket ile ılgili olarak aşağıda belirtilen hususlar müdürlüğümüze\nibraz edilen belgelere istinaden ve Türk Ticaret Kanunu'na uygun olarak 26.3.2025\ntarihinde tescil edildiği ilan olunur.\nTescil Edilen Hususlar:Şirketm Unvanı\nTescile Delil Olan Belgeler:Bakırköy 45. noterliği! Nin 26.3.2025 Tarih 7432 Sayı İle\nTasdıklı, 25.3.2025 Tarıhlı 02 Sayılı Genel Kurul Kararı\nİÇERİĞİ DEĞİŞEN MADDELERİN YENİ HALİ\nŞİRKETİN UNVANI\nMadde 2-\nŞirketin unvanı MESUT MÜTEAHHİTLİK GAYRİMENKUL OTOMOTİV İNŞAAT\nMALZEMELERİ LİMİTED ŞİRKETİ 'dir.",
  "box_id": "20060893"
}